MANIFEST.in
README.md
requirements.txt
setup.cfg
setup.py
kill_mustache/__init__.py
kill_mustache/kill_mustache.py
kill_mustache.egg-info/PKG-INFO
kill_mustache.egg-info/SOURCES.txt
kill_mustache.egg-info/dependency_links.txt
kill_mustache.egg-info/requires.txt
kill_mustache.egg-info/top_level.txt