Metadata-Version: 1.1
Name: kill-mustache
Version: 0.0.1
Summary: remove to mustache file
Home-page: https://github.com/Vinicius-rodrigues/kill_mustache
Author: Vinicius Rodrigues Silva
Author-email: viniciusrodrigues93@yahoo.com.br
License: BSD
Download-URL: https://github.com/Vinicius-rodrigues/Kill_mustache/archive/0.0.1.tar.gz
Keywords: mustache,kill
Platform: UNKNOWN
Classifier: Development Status :: 3 - Alpha
Classifier: Intended Audience :: Developers
Classifier: Programming Language :: Python :: 3
